enam/__init__.py
enam/datautils.py
enam/evaluate.py
enam/execute.py
enam/header.py
enam/utils.py
enam-0.2.0.dist-info/LICENSE
enam-0.2.0.dist-info/METADATA
enam-0.2.0.dist-info/WHEEL
enam-0.2.0.dist-info/top_level.txt
enam-0.2.0.dist-info/RECORD
