Metadata-Version: 2.1
Name: enam
Version: 0.2.0
Summary: "ENAMEL: A benchmark for evaluating the capability of LLMs in generating efficient code"
Home-page: https://github.com/q-rz/enamel
Author: Qiu et al.
Author-email: rq5@illinois.edu
License: Apache-2.0
Project-URL: Repository, https://github.com/q-rz/enamel
Project-URL: Issues, https://github.com/q-rz/enamel/issues
Classifier: Programming Language :: Python :: 3
Classifier: License :: OSI Approved :: Apache Software License
Classifier: Topic :: Scientific/Engineering :: Artificial Intelligence
Requires-Python: >=3.10
License-File: LICENSE
Requires-Dist: tqdm >=3.1.4
Requires-Dist: numpy >=1.4.0
Requires-Dist: pandas >=1.0
